h5analysis/LoadData.py
h5analysis/MathData.py
h5analysis/ReadData.py
h5analysis/__init__.py
h5analysis/_version.py
h5analysis/beamline_info.py
h5analysis/config.py
h5analysis/data_1d.py
h5analysis/data_2d.py
h5analysis/data_3d.py
h5analysis/datautil.py
h5analysis/histogram.py
h5analysis/interpolate.py
h5analysis/parser.py
h5analysis/plot_exporter.py
h5analysis/readutil.py
h5analysis/scatter.py
h5analysis/simplemath.py
h5analysis/util.py
h5analysis/validation.py
h5analysis/beamlines/REIXS.py
h5analysis/beamlines/__init__.py
h5analysis/static/__init__.py
h5analysis-0.1.16.post0.dist-info/licenses/LICENSE
h5analysis-0.1.16.post0.dist-info/METADATA
h5analysis-0.1.16.post0.dist-info/WHEEL
h5analysis-0.1.16.post0.dist-info/top_level.txt
h5analysis-0.1.16.post0.dist-info/RECORD
