Metadata-Version: 2.4
Name: h5analysis
Version: 0.1.16.post0
Summary: Library to analyse, plot, and export data stored in HDF5 files.
Home-page: https://github.com/pmb399/H5Analysis
Author: Patrick Braun
Author-email: patrick.braun@usask.ca
License: MIT License
Project-URL: Documentation, https://h5analysis.readthedocs.io/latest/
Project-URL: Source, https://github.com/pmb399/H5Analysis
Project-URL: Tutorial, https://reixs.lightsource.ca/workshops/reixs-sxs-workshop-2023/
Project-URL: Bug Tracker, https://github.com/pmb399/H5Analysis/issues
Project-URL: Canadian Light Source, https://lightsource.ca
Project-URL: HDF Group, https://www.hdfgroup.org/
Project-URL: NeXus, https://manual.nexusformat.org/
Classifier: Intended Audience :: Science/Research
Classifier: Intended Audience :: Information Technology
Classifier: Programming Language :: Python :: 3
Classifier: License :: OSI Approved :: MIT License
Classifier: Operating System :: OS Independent
Classifier: Development Status :: 3 - Alpha
Classifier: Framework :: Jupyter
Classifier: Topic :: Scientific/Engineering :: Physics
Classifier: Topic :: Scientific/Engineering :: Visualization
Classifier: Topic :: Scientific/Engineering :: Chemistry
Classifier: Natural Language :: English
Requires-Python: >=3.9
License-File: LICENSE
Requires-Dist: numpy==2.0.2
Requires-Dist: pandas==2.2.3
Requires-Dist: bokeh==3.4.3
Requires-Dist: scipy==1.13.1
Requires-Dist: ipywidgets==8.1.5
Requires-Dist: ipyfilechooser==0.6.0
Requires-Dist: h5py==3.13.0
Requires-Dist: shapely==2.0.7
Requires-Dist: parse==1.20.2
Requires-Dist: scikit-image==0.24.0
Requires-Dist: colorcet==3.1.0
Requires-Dist: matplotlib==3.9.4
Requires-Dist: lmfit==1.3.2
Requires-Dist: notebook==6.5.7
Requires-Dist: uncertainties==3.2.2
Requires-Dist: ffmpeg==1.4
Provides-Extra: exafs
Requires-Dist: xraylarch>=0.9.71; extra == "exafs"
Provides-Extra: baseline
Requires-Dist: pybaselines>=1.1.0; extra == "baseline"
Dynamic: license-file
